remember_me/__init__.py
remember_me/starlist_manager.py
remember_me/vocab_loader.py
remember_me/vocab_practice.py
remember_me_gre-1.0.1.dist-info/LICENSE
remember_me_gre-1.0.1.dist-info/METADATA
remember_me_gre-1.0.1.dist-info/WHEEL
remember_me_gre-1.0.1.dist-info/entry_points.txt
remember_me_gre-1.0.1.dist-info/top_level.txt
remember_me_gre-1.0.1.dist-info/RECORD
