Metadata-Version: 2.1
Name: remember-me-gre
Version: 1.0.1
Summary: A GRE vocabulary practice tool with AI assistance
Home-page: https://github.com/Peter00796/remember_me.git
Author: Yanxin Peng
Author-email: peterpen@usc.edu
License: MIT
Classifier: Programming Language :: Python :: 3
Classifier: License :: OSI Approved :: MIT License
Classifier: Operating System :: OS Independent
Requires-Python: >=3.7
License-File: LICENSE
Requires-Dist: openai (>=0.27.0)
Requires-Dist: colorama (>=0.4.6)
